efficax/__init__.py
efficax/main.py
efficax-0.1.1.dist-info/METADATA
efficax-0.1.1.dist-info/WHEEL
efficax-0.1.1.dist-info/top_level.txt
efficax-0.1.1.dist-info/RECORD
