Metadata-Version: 2.4
Name: efficax
Version: 0.1.1
Summary: Extracts text from PDFs between keywords and adds rectangle overlays using PyMuPDF.
Author: masu
Keywords: pdf,pymupdf,text extraction,overlay,automation
Requires-Python: >=3.9
Requires-Dist: pymupdf>=1.24.0
Requires-Dist: pandas>=2.0.0
